pyzerox/__init__.py
pyzerox/constants/__init__.py
pyzerox/constants/conversion.py
pyzerox/constants/messages.py
pyzerox/constants/patterns.py
pyzerox/constants/prompts.py
pyzerox/core/__init__.py
pyzerox/core/types.py
pyzerox/core/zerox.py
pyzerox/errors/__init__.py
pyzerox/errors/base.py
pyzerox/errors/exceptions.py
pyzerox/models/__init__.py
pyzerox/models/base.py
pyzerox/models/modellitellm.py
pyzerox/models/types.py
pyzerox/processor/__init__.py
pyzerox/processor/image.py
pyzerox/processor/pdf.py
pyzerox/processor/text.py
pyzerox/processor/utils.py
scripts/__init__.py
scripts/pre_install.py
py_zerox-0.0.7.dist-info/LICENSE
py_zerox-0.0.7.dist-info/METADATA
py_zerox-0.0.7.dist-info/WHEEL
py_zerox-0.0.7.dist-info/entry_points.txt
py_zerox-0.0.7.dist-info/top_level.txt
py_zerox-0.0.7.dist-info/RECORD
