Metadata-Version: 2.1
Name: py-zerox
Version: 0.0.7
Summary: ocr documents using vision models from all popular providers like OpenAI, Azure OpenAI, Anthropic, AWS Bedrock etc
Author: wizenheimer, pradhyumna85
License: MIT
Classifier: License :: OSI Approved :: MIT License
Classifier: Programming Language :: Python :: 3
Classifier: Programming Language :: Python :: 3.11
Requires-Python: >=3.11
License-File: LICENSE
Requires-Dist: aiofiles>=23.0
Requires-Dist: aiohttp>=3.9.5
Requires-Dist: pdf2image>=1.17.0
Requires-Dist: litellm>=1.44.15
Requires-Dist: aioshutil>=1.5
Requires-Dist: PyPDF2>=3.0.1
